LICENSE
README.md
setup.py
memwin/__init__.py
memwin/constants.py
memwin/structs.py
memwin/utils.py
memwin/version.py
memwin/xapi.py
memwin/xmemory.py
memwin/xprocess.py
memwin/xthread.py
memwin.egg-info/PKG-INFO
memwin.egg-info/SOURCES.txt
memwin.egg-info/dependency_links.txt
memwin.egg-info/requires.txt
memwin.egg-info/top_level.txt