Metadata-Version: 2.1
Name: memwin
Version: 1.9.8
Summary: 一个python操作windows的 进程,线程,内存读写,DLL注入的库
Home-page: https://github.com/decenfrontier/memwin
Author: decenfrontier
Author-email: decenfrontier@gmail.com
License: MIT License
Platform: win32
Classifier: Operating System :: OS Independent
Classifier: Programming Language :: Python :: 3
Requires-Python: >=3.8
